mb_drf_article/__init__.py
mb_drf_article/admin.py
mb_drf_article/apps.py
mb_drf_article/migrations/__init__.py
mb_drf_article/models.py
mb_drf_article/permissions.py
mb_drf_article/serializers.py
mb_drf_article/tests.py
mb_drf_article/urls.py
mb_drf_article/views.py
mb_drf_article-0.1.2.dist-info/WHEEL
mb_drf_article-0.1.2.dist-info/METADATA
mb_drf_article-0.1.2.dist-info/RECORD
